{
  "content": [
    {
      "content": null,
      "created": "2022-03-02T18:01:53.374158Z",
      "format": null,
      "last_modified": "2022-03-02T18:00:50.853423Z",
      "mimetype": "application/pdf",
      "name": "10_mastermind.pdf",
      "path": "2_tp_semestre1/10_mastermind.pdf",
      "size": 109658,
      "type": "file",
      "writable": true
    },
    {
      "content": null,
      "created": "2022-03-02T18:01:53.378158Z",
      "format": null,
      "last_modified": "2022-03-02T18:00:50.853423Z",
      "mimetype": null,
      "name": "4_dichotomie.ipynb",
      "path": "2_tp_semestre1/4_dichotomie.ipynb",
      "size": 9096,
      "type": "notebook",
      "writable": true
    },
    {
      "content": null,
      "created": "2022-03-02T18:01:53.398159Z",
      "format": null,
      "last_modified": "2022-03-02T18:00:50.889424Z",
      "mimetype": null,
      "name": "9_tris.ipynb",
      "path": "2_tp_semestre1/9_tris.ipynb",
      "size": 8082,
      "type": "notebook",
      "writable": true
    },
    {
      "content": null,
      "created": "2022-03-02T18:01:53.378158Z",
      "format": null,
      "last_modified": "2022-03-02T18:00:50.853423Z",
      "mimetype": null,
      "name": "5_recursivite.ipynb",
      "path": "2_tp_semestre1/5_recursivite.ipynb",
      "size": 14190,
      "type": "notebook",
      "writable": true
    },
    {
      "content": null,
      "created": "2022-03-02T18:01:53.374158Z",
      "format": null,
      "last_modified": "2022-03-02T18:01:53.374158Z",
      "mimetype": null,
      "name": "11_puissance4",
      "path": "2_tp_semestre1/11_puissance4",
      "size": null,
      "type": "directory",
      "writable": true
    },
    {
      "content": null,
      "created": "2022-03-02T18:01:53.378158Z",
      "format": null,
      "last_modified": "2022-03-02T18:00:50.853423Z",
      "mimetype": null,
      "name": "1_dictionnaire.ipynb",
      "path": "2_tp_semestre1/1_dictionnaire.ipynb",
      "size": 12445,
      "type": "notebook",
      "writable": true
    },
    {
      "content": null,
      "created": "2022-03-02T18:01:53.378158Z",
      "format": null,
      "last_modified": "2022-03-02T18:00:50.853423Z",
      "mimetype": null,
      "name": "7_glouton.ipynb",
      "path": "2_tp_semestre1/7_glouton.ipynb",
      "size": 17467,
      "type": "notebook",
      "writable": true
    },
    {
      "content": null,
      "created": "2022-03-02T18:01:53.378158Z",
      "format": null,
      "last_modified": "2022-03-02T18:00:50.853423Z",
      "mimetype": null,
      "name": "2_boucles_imbriquees.ipynb",
      "path": "2_tp_semestre1/2_boucles_imbriquees.ipynb",
      "size": 12934,
      "type": "notebook",
      "writable": true
    },
    {
      "content": null,
      "created": "2022-03-02T18:01:53.386158Z",
      "format": null,
      "last_modified": "2022-03-02T18:00:50.889424Z",
      "mimetype": null,
      "name": "8_matrice_image.ipynb",
      "path": "2_tp_semestre1/8_matrice_image.ipynb",
      "size": 6436347,
      "type": "notebook",
      "writable": true
    },
    {
      "content": null,
      "created": "2022-03-02T18:01:53.378158Z",
      "format": null,
      "last_modified": "2022-03-02T18:00:50.853423Z",
      "mimetype": null,
      "name": "3_module.ipynb",
      "path": "2_tp_semestre1/3_module.ipynb",
      "size": 12763,
      "type": "notebook",
      "writable": true
    },
    {
      "content": null,
      "created": "2022-03-02T18:01:53.378158Z",
      "format": null,
      "last_modified": "2022-03-02T18:00:50.853423Z",
      "mimetype": null,
      "name": "6_fractales.ipynb",
      "path": "2_tp_semestre1/6_fractales.ipynb",
      "size": 274740,
      "type": "notebook",
      "writable": true
    },
    {
      "content": null,
      "created": "2022-03-02T18:01:53.398159Z",
      "format": null,
      "last_modified": "2022-03-02T18:00:50.893425Z",
      "mimetype": "image/jpeg",
      "name": "paris.jpg",
      "path": "2_tp_semestre1/paris.jpg",
      "size": 88651,
      "type": "file",
      "writable": true
    }
  ],
  "created": "2022-03-02T18:01:53.398159Z",
  "format": "json",
  "last_modified": "2022-03-02T18:01:53.398159Z",
  "mimetype": null,
  "name": "2_tp_semestre1",
  "path": "2_tp_semestre1",
  "size": null,
  "type": "directory",
  "writable": true
}